ai_xone_mcp_workflow/__init__.py
ai_xone_mcp_workflow/server.py
ai_xone_mcp_workflow/workflow_model.py
ai_xone_mcp_workflow/workflow_repository.py
ai_xone_mcp_workflow/tasks/__init__.py
ai_xone_mcp_workflow/tasks/ai_task.py
ai_xone_mcp_workflow/tasks/base.py
ai_xone_mcp_workflow/tasks/mcp_task.py
ai_xone_mcp_workflow-0.0.2a5.dist-info/METADATA
ai_xone_mcp_workflow-0.0.2a5.dist-info/WHEEL
ai_xone_mcp_workflow-0.0.2a5.dist-info/entry_points.txt
ai_xone_mcp_workflow-0.0.2a5.dist-info/top_level.txt
ai_xone_mcp_workflow-0.0.2a5.dist-info/RECORD
