Metadata-Version: 2.4
Name: ai_xone_mcp_workflow
Version: 0.0.2a5
Summary: Workflow module for ai_xone_mcp
Author-email: 80pc <80pc@aliyun.com>
Requires-Python: <4.0,>=3.10
Requires-Dist: fastmcp==2.3.5
Requires-Dist: pyyaml==6.0.1
